asyncdb/__init__.py
asyncdb/_version.py
asyncdb/connections.py
asyncdb/py.typed
asyncdb/version.py
asyncdb/conversions/__init__.py
asyncdb/conversions/pgrecords.py
asyncdb/conversions/rst_convert/Cargo.lock
asyncdb/conversions/rst_convert/Cargo.toml
asyncdb/conversions/rst_convert/src/lib.rs
asyncdb/conversions/rst_convert/target/.rustc_info.json
asyncdb/conversions/rst_convert/target/CACHEDIR.TAG
asyncdb/conversions/rst_convert/target/release/.cargo-lock
asyncdb/conversions/rst_convert/target/release/librst_convert.d
asyncdb/conversions/rst_convert/target/release/.fingerprint/ahash-5653aaf2556c8002/dep-lib-ahash
asyncdb/conversions/rst_convert/target/release/.fingerprint/ahash-5653aaf2556c8002/invoked.timestamp
asyncdb/conversions/rst_convert/target/release/.fingerprint/ahash-5653aaf2556c8002/lib-ahash
asyncdb/conversions/rst_convert/target/release/.fingerprint/ahash-5653aaf2556c8002/lib-ahash.json
asyncdb/conversions/rst_convert/target/release/.fingerprint/ahash-ebc0fcf21098b49a/build-script-build-script-build
asyncdb/conversions/rst_convert/target/release/.fingerprint/ahash-ebc0fcf21098b49a/build-script-build-script-build.json
asyncdb/conversions/rst_convert/target/release/.fingerprint/ahash-ebc0fcf21098b49a/dep-build-script-build-script-build
asyncdb/conversions/rst_convert/target/release/.fingerprint/ahash-ebc0fcf21098b49a/invoked.timestamp
asyncdb/conversions/rst_convert/target/release/.fingerprint/ahash-f7164d461363db4c/run-build-script-build-script-build
asyncdb/conversions/rst_convert/target/release/.fingerprint/ahash-f7164d461363db4c/run-build-script-build-script-build.json
asyncdb/conversions/rst_convert/target/release/.fingerprint/array-init-cursor-6f832fd46a523cb9/dep-lib-array_init_cursor
asyncdb/conversions/rst_convert/target/release/.fingerprint/array-init-cursor-6f832fd46a523cb9/invoked.timestamp
asyncdb/conversions/rst_convert/target/release/.fingerprint/array-init-cursor-6f832fd46a523cb9/lib-array_init_cursor
asyncdb-2.13.2.dist-info/licenses/LICENSE
asyncdb-2.13.2.dist-info/METADATA
asyncdb-2.13.2.dist-info/WHEEL
asyncdb-2.13.2.dist-info/top_level.txt
asyncdb-2.13.2.dist-info/RECORD
